mongodec/__init__.py
mongodec/changeling.py
mongodec/filter_mongo.py
mongodec/mongodec.py
mongodec/tests/__init__.py
mongodec/tests/test_changeling.py
mongodec/tests/test_filter_mongo.py
mongodec/tests/test_mongodec.py
mongodec-1.0.16.dist-info/DESCRIPTION.rst
mongodec-1.0.16.dist-info/METADATA
mongodec-1.0.16.dist-info/RECORD
mongodec-1.0.16.dist-info/WHEEL
mongodec-1.0.16.dist-info/entry_points.txt
mongodec-1.0.16.dist-info/metadata.json
mongodec-1.0.16.dist-info/top_level.txt
