Metadata-Version: 2.0
Name: mongodec
Version: 1.0.16
Summary: Wrapper classes with an application for Mongo
Home-page: https://github.com/revbucket/mongodec
Author: Matt Jordan
Author-email: mattjordan.mail@gmail.com
License: BSD
Keywords: wrapper mongo filter
Platform: UNKNOWN
Classifier: Development Status :: 5 - Production/Stable
Classifier: Intended Audience :: Developers
Classifier: Topic :: Software Development :: Build Tools
Classifier: License :: OSI Approved :: BSD License
Classifier: Programming Language :: Python :: 2
Classifier: Programming Language :: Python :: 2.6
Classifier: Programming Language :: Python :: 2.7
Requires-Dist: pymongo
Provides-Extra: dev
Requires-Dist: check-manifest; extra == 'dev'
Provides-Extra: test
Requires-Dist: coverage; extra == 'test'
